{"id":"Focm","dependencies":[{"name":"/home/sdml/Bureau/ini-parser/package.json","includedInParent":true,"mtime":1574937680360}],"generated":{"js":"\"use strict\";Object.defineProperty(exports,\"__esModule\",{value:!0});var t=function(){return function(t,r){if(Array.isArray(t))return t;if(Symbol.iterator in Object(t))return function(t,r){var e=[],n=!0,i=!1,u=void 0;try{for(var a,o=t[Symbol.iterator]();!(n=(a=o.next()).done)&&(e.push(a.value),!r||e.length!==r);n=!0);}catch(t){i=!0,u=t}finally{try{!n&&o.return&&o.return()}finally{if(i)throw u}}return e}(t,r);throw new TypeError(\"Invalid attempt to destructure non-iterable instance\")}}(),r=function(r){var e=arguments.length>1&&void 0!==arguments[1]?arguments[1]:{},n=\"\";return r.split(/[\\n]+/g).filter(function(t){return t.trim()&&!t.match(/^\\s*[;#]/)}).map(function(t){return t.match(/^\\[([^\\]]*)\\]$|^([^=]+)(=(.*))?$/i)}).map(function(r){var i=r.map(function(t){return t&&t.trim()}),u=t(i,5),a=u[1],o=u[2],l=u[4];if(a)n=a;else{if(\"string\"==typeof l&&\"$\"==l.charAt(0)){var s=e;l.slice(1).split(/\\./).map(function(t){s=s[t]}),l=s}\"string\"!=typeof l||\"+\"!=l.charAt(0)||isNaN(l.slice(1))||(l=+l),-1!=[\"true\",\"false\",\"null\"].indexOf(l)&&(l=JSON.parse(l)),o.length>2&&\"[]\"===o.slice(-2)?(o=o.substring(0,o.length-2),n?(e[n]&&!e[n][o]&&(e[n][o]=[]),e[n][o].push(l)):(e[o]||(e[o]=[]),e[o].push(l))):\"\"==n?e[o]=l:(e[n]||(e[n]={}),e[n][o]=l)}}),e};exports.default=r;","map":null},"hash":"004971346b157ee106aefae5029838f1","cacheData":{"env":{}}}